{"name":"t:sections.footer.name","type":"footer","sections":{"footer":{"type":"footer","blocks":{"983a58d5-b3ca-48f5-b9e4-8a8727ac42ab":{"type":"link_list","settings":{"heading":"Categories","menu":"categories"}},"83030e7e-7893-468d-8f0d-1b1e09547bd9":{"type":"link_list","settings":{"heading":"Information","menu":"information"}},"a7d537f4-b540-4527-8c29-06cbd94ef0ec":{"type":"link_list","settings":{"heading":"My Account","menu":"my-account"}},"bcf43cbd-f4c9-4c5e-940b-d914df764e4d":{"type":"link_list","settings":{"heading":"Other Information","menu":"other-information"}}},"block_order":["983a58d5-b3ca-48f5-b9e4-8a8727ac42ab","83030e7e-7893-468d-8f0d-1b1e09547bd9","a7d537f4-b540-4527-8c29-06cbd94ef0ec","bcf43cbd-f4c9-4c5e-940b-d914df764e4d"],"settings":{"color_scheme":"scheme-e2b17b3f-09b1-4b41-b299-35211db7b8ac","show_footer_bottom_content":false,"socialmedia_block_heading":"Follow Us On","newsletter_enable":false,"newsletter_heading":"Subscribe to our emails","enable_follow_on_shop":true,"show_social":true,"enable_country_selector":true,"enable_language_selector":true,"payment_enable":true,"show_policy":false,"margin_top":0,"padding_top":0,"padding_bottom":0}}},"order":["footer"]}